Metadata-Version: 1.1
Name: CASWSGIMiddleware
Version: 1.1.0
Summary: A WSGI middleware module to enable CAS authentication
Home-page: https://github.com/wrighting/cas_wsgi_middleware
Author: Ian Wright
Author-email: tech@wrighting.org
License: UNKNOWN
Keywords: cas wsgi python
Platform: UNKNOWN
Classifier: Development Status :: 5 - Production/Stable
Classifier: Programming Language :: Python :: 2
